{
  "Modifiers": {
    "upgrade_attack": {
      "name": "Upgrade Attack",
      "value": 3,
      "multiplier": 0,
      "sType": "DMG_PHYSICAL",
      "mType": "UNIT_MOD",
      "text": "Upgrade: +VALUE power",
      "mText": "Upgrade: +VALUE power"
    },
    "upgrade_stamina": {
      "name": "Upgrade Stamina",
      "value": 1,
      "multiplier": 0,
      "sType": "STAMINA",
      "mType": "UNIT_MOD",
      "text": "Upgrade: +VALUE stamina",
      "mText": "Upgrade: +VALUE stamina"
    },
    "eot_stamina": {
      "name": "Stamina Reduced",
      "value": 0,
      "multiplier": 0,
      "sType": "STAMINA",
      "mType": "UNIT_MOD",
      "EOTChange": -1,
      "text": "Stamina reduced each turn",
      "mText": "Stamina reduced each turn"
    },
    "aura_empress_shrine": {
      "name": "Empress Shrine Aura",
      "value": 2,
      "multiplier": 0,
      "sType": "DMG_PHYSICAL",
      "mType": "AURA_MOD",
      "text": "AURA: Friendly units gain\n\t +VALUE power",
      "mText": "Shrine: +VALUE power"
    },
    "rage_modifier": {
      "name": "Rage Modifier",
      "value": 2,
      "multiplier": 0,
      "sType": "DMG_PHYSICAL",
      "mType": "UNIT_MOD",
      "text": "Friendly units gain +VALUE\n\t power",
      "mText": "Rage: +VALUE power"
    },
    "remove_stamina_modifier": {
      "name": "Remove Stamina Modifier",
      "value": -9,
      "multiplier": 0,
      "sType": "STAMINA",
      "mType": "UNIT_MOD",
      "text": "Reduce the highest power\n unit's stamina by VALUE",
      "mText": "Sapped: Stamina reduced by VALUE"
    },
    "big_frog_buff": {
      "name": "Big Frog Buff",
      "value": 1,
      "multiplier": 0,
      "sType": "DMG_PHYSICAL",
      "mType": "UNIT_MOD",
      "EOTChange": 0,
      "text": "Friendly units gain +VALUE\n\tpower each turn",
      "mText": "Big Frog: +VALUE power"
    },
    "big_frog_modifier": {
      "name": "Big Frog Modifier",
      "value": 0,
      "multiplier": 0,
      "sType": "DMG_PHYSICAL",
      "mType": "AURA_EOT_MOD",
      "EOTChange": 1,
      "text": "Friendly units gain\n EOTCHANGE attack each turn",
      "mText": "Big Frog: +EOTCHANGE power each turn",
      "modifier": "big_frog_buff"
    },
    "spy_frog_buff": {
      "name": "Spy Frog Buff",
      "value": -1,
      "multiplier": 0,
      "sType": "DMG_PHYSICAL",
      "mType": "UNIT_MOD",
      "EOTChange": 0,
      "text": "Zone units lose VALUE\n\tpower each turn",
      "mText": "Spy Frog: Lost VALUE power"
    },
    "spy_frog_modifier": {
      "name": "Big Frog Modifier",
      "value": 0,
      "multiplier": 0,
      "sType": "DMG_PHYSICAL",
      "mType": "AURA_EOT_MOD",
      "EOTChange": -1,
      "text": "Zone units lose EOTCHANGE power\n\t each turn",
      "mText": "Spy Frog: Lose EOTCHANGE power\n\t\t each turn",
      "modifier": "spy_frog_buff"
    },
    "guard_frog_modifier": {
      "name": "Guard Frog Modifier",
      "value": 0,
      "multiplier": 0,
      "sType": "ARMOUR_PHYSICAL",
      "mType": "PLAYER_EOT_MOD",
      "EOTChange": 1,
      "text": "Gain EOTCHANGE Armour each turn.",
      "mText": "Gain EOTCHANGE Armour each turn."
    },
    "mystic_frog_modifier": {
      "name": "Mystic Frog Modifier",
      "value": -1,
      "multiplier": 0,
      "sType": "EFFECT_COST",
      "mType": "PLAYER_MOD",
      "EOTChange": 0,
      "text": "Effects cards cost VALUE\nless to play.",
      "mText": "Effects cards cost VALUE\nless to play."
    },
    "jog_frog_modifier": {
      "name": "Jog Frog Modifier",
      "value": 0,
      "multiplier": 0,
      "sType": "ARMOUR_PHYSICAL",
      "mType": "SWAP_ZONE",
      "EOTChange": 1,
      "text": "Moves to the other zone\nat the end of each turn.",
      "mText": "Moves to the other zone\nat the end of each turn."
    },
    "general_frog_modifier": {
      "name": "Guard Frog Modifier",
      "value": 1,
      "multiplier": 0,
      "sType": "DMG_PHYSICAL",
      "mType": "ZONE_MOD_ATTACK",
      "EOTChange": 0,
      "text": "Units in the Attack Zone\ngain VALUE attack.",
      "mText": "Units in the Attack Zone\ngain VALUE attack."
    },
    "banner_frog_modifier": {
      "name": "Banner Frog Modifier",
      "value": -1,
      "multiplier": 0,
      "sType": "UNIT_COST",
      "mType": "PLAYER_MOD",
      "EOTChange": 0,
      "text": "Unit cards cost VALUE\nless to play.",
      "mText": "Unit cards cost VALUE\nless to play."
    },
    "power_ribbit_modifier": {
      "name": "Power Ribbit Modifier",
      "value": -1,
      "multiplier": 0,
      "sType": "STAMINA",
      "mType": "UNIT_MOD",
      "EOTChange": 0,
      "text": "Power Ribbit: Lost VALUE stamina.",
      "mText": "Power Ribbit: Lost VALUE stamina."
    },
    "musical_modifier": {
      "name": "Musical Modifier",
      "value": 0,
      "multiplier": 0,
      "sType": "STAMINA",
      "mType": "UNIT_MOD",
      "EOTChange": 0,
      "text": "MUSICAL",
      "mText": "MUSICAL"
    },
    "flute_frog_modifier": {
      "name": "Flute Frog Modifier",
      "value": 1,
      "multiplier": 0,
      "sType": "DMG_PHYSICAL",
      "mType": "MUSIC_AURA",
      "EOTChange": 0,
      "text": "MUSICAL units gain VALUE attack.",
      "mText": "MUSICAL units gain VALUE attack."
    },
    "drum_frog_modifier": {
      "name": "Drum Frog Modifier",
      "value": 1,
      "multiplier": 0,
      "sType": "DMG_PHYSICAL",
      "mType": "MUSIC_AURA",
      "EOTChange": 0,
      "text": "MUSICAL units gain VALUE attack.",
      "mText": "MUSICAL units gain VALUE attack."
    },
    "horn_frog_modifier": {
      "name": "Horn Frog Modifier",
      "value": 1,
      "multiplier": 0,
      "sType": "DMG_PHYSICAL",
      "mType": "MUSIC_AURA",
      "EOTChange": 0,
      "text": "MUSICAL units gain VALUE attack.",
      "mText": "MUSICAL units gain VALUE attack."
    },
    "tuba_frog_modifier": {
      "name": "Tuba Frog Modifier",
      "value": 1,
      "multiplier": 0,
      "sType": "DMG_PHYSICAL",
      "mType": "MUSIC_AURA",
      "EOTChange": 0,
      "text": "MUSICAL units gain VALUE attack.",
      "mText": "MUSICAL units gain VALUE attack."
    },
    "spear_frog_modifier": {
      "name": "Spear Frog Modifier",
      "value": -2,
      "multiplier": 0,
      "sType": "DMG_PHYSICAL",
      "mType": "OPPOSITE_ZONE",
      "EOTChange": 0,
      "text": "Enemy units opposite Spear\nFrog lose VALUE attack.",
      "mText": "Spear Frog: Lose VALUE attack"
    },
    "bog_frog_modifier": {
      "name": "Bog Frog Modifier",
      "value": -3,
      "multiplier": 0,
      "sType": "STAMINA",
      "mType": "OPPOSITE_ZONE",
      "EOTChange": 0,
      "text": "Enemy units opposite bog\nFrog lose VALUE stamina.",
      "mText": "Spear Frog: Lose VALUE attack"
    },
    "ogre_buff": {
      "name": "Ogre Buff",
      "value": 4,
      "multiplier": 0,
      "sType": "DMG_PHYSICAL",
      "mType": "UNIT_MOD",
      "EOTChange": 0,
      "text": "Ogre gains +VALUE power\n\t each turn",
      "mText": "Ogre: +VALUE power"
    },
    "ogre_modifier": {
      "name": "Ogre Modifier",
      "value": 0,
      "multiplier": 0,
      "sType": "DMG_PHYSICAL",
      "mType": "UNIT_EOT_MOD",
      "EOTChange": 4,
      "text": "Ogre gains +EOTCHANGE power\n\t each turn",
      "mText": "Ogre: +EOTCHANGE power each turn",
      "modifier": "ogre_buff"
    },
    "troll_buff": {
      "name": "Troll Buff",
      "value": 4,
      "multiplier": 0,
      "sType": "DMG_PHYSICAL",
      "mType": "UNIT_MOD",
      "EOTChange": 4,
      "text": "Friendly units gain +EOTCHANGE power\n\t each turn",
      "mText": "Troll Boss: +EOTCHANGE power"

    },
    "troll_rage": {
      "name": "Troll Rage",
      "value": 0,
      "multiplier": 0,
      "sType": "DMG_PHYSICAL",
      "mType": "AURA_EOT_MOD",
      "EOTChange": 4,
      "text": "Friendly units gain +EOTCHANGE power\n\t each turn",
      "mText": "Troll Boss: +EOTCHANGE power\n\t\t\teach turn",
      "modifier": "troll_buff"
    },

    "boss_resist": {
      "name": "Boss Resist",
      "value": 0,
      "multiplier": 0,
      "sType": "DMG_PHYSICAL",
      "mType": "BOSS_RESIST_MOD",
      "EOTChange": 0,
      "text": "Bossy",
      "mText": "BOSS:No Stamina loss\n\t  each round"
    }
  }
}
